<Properties StartupConfiguration="{20D308BF-832F-49F9-B230-472ABA0C35D6}|Default">
  <MonoDevelop.Ide.ItemProperties.PG__Management__MongoDB PreferredExecutionTarget="MonoDevelop.Default" />
  <MonoDevelop.Ide.Workbench>
    <Pads>
      <Pad Id="ProjectPad">
        <State name="__root__">
          <Node name="PG_Management_MongoDB" expanded="True">
            <Node name="PG_Management_MongoDB" expanded="True">
              <Node name="Dependencies" expanded="True">
                <Node name="PackageDependencies" expanded="True" />
              </Node>
              <Node name="Controllers" expanded="True" />
              <Node name="Models" expanded="True" />
              <Node name="Services" expanded="True">
                <Node name="TenantServices.cs" selected="True" />
              </Node>
            </Node>
          </Node>
        </State>
      </Pad>
    </Pads>
  </MonoDevelop.Ide.Workbench>
  <MonoDevelop.Ide.DebuggingService.PinnedWatches />
  <MonoDevelop.Ide.Workspace ActiveConfiguration="Debug" />
  <MonoDevelop.Ide.DebuggingService.Breakpoints>
    <BreakpointStore />
  </MonoDevelop.Ide.DebuggingService.Breakpoints>
  <MultiItemStartupConfigurations />
</Properties>